hypothesis_010/__init__.py
hypothesis_010/py.typed
hypothesis_asn1/__init__.py
hypothesis_asn1/py.typed
hypothesis_asn1-0.0.1.dist-info/LICENSE
hypothesis_asn1-0.0.1.dist-info/METADATA
hypothesis_asn1-0.0.1.dist-info/WHEEL
hypothesis_asn1-0.0.1.dist-info/top_level.txt
hypothesis_asn1-0.0.1.dist-info/RECORD
