Metadata-Version: 2.1
Name: hypothesis-asn1
Version: 0.0.1
Summary: Generate test data from ASN.1 descriptions with Hypothesis
Home-page: https://github.com/Zac-HD/hypothesis-asn1
Author: Zac Hatfield-Dodds
Author-email: zac@zhd.dev
License: MPL 2.0
Keywords: python testing fuzzing property-based-testing ASN.1
Platform: UNKNOWN
Classifier: Development Status :: 1 - Planning
Classifier: Framework :: Hypothesis
Classifier: Intended Audience :: Developers
Classifier: License :: OSI Approved :: Mozilla Public License 2.0 (MPL 2.0)
Classifier: Programming Language :: Python
Classifier: Programming Language :: Python :: 3
Classifier: Programming Language :: Python :: 3.6
Classifier: Programming Language :: Python :: 3.7
Classifier: Programming Language :: Python :: 3.8
Classifier: Programming Language :: Python :: 3.9
Classifier: Topic :: Software Development :: Testing
Classifier: Typing :: Typed
Requires-Python: >=3.6
Requires-Dist: hypothesis (>=6.0.0)
Requires-Dist: pyasn1 (>=0.4.8)
